contentfiles/__init__.py
contentfiles/storage.py
devsoc_contentfiles-0.5.dist-info/licenses/LICENSE
devsoc_contentfiles-0.5.dist-info/METADATA
devsoc_contentfiles-0.5.dist-info/WHEEL
devsoc_contentfiles-0.5.dist-info/top_level.txt
devsoc_contentfiles-0.5.dist-info/RECORD
